multitessiocr/README.MD
multitessiocr/__init__.py
multitessiocr/requirements.txt
multitessiocr/thirdparty.json
multitessiocr-0.12.dist-info/LICENSE.rst
multitessiocr-0.12.dist-info/METADATA
multitessiocr-0.12.dist-info/WHEEL
multitessiocr-0.12.dist-info/top_level.txt
multitessiocr-0.12.dist-info/RECORD
