Metadata-Version: 2.1
Name: multitessiocr
Version: 0.12
Summary: Performs a very fast OCR on a list of images (file path, url, base64, bytes, numpy, PIL ...) using Tesseract and returns the recognized text, its coordinates, and line-based word grouping in a DataFrame.
Home-page: https://github.com/hansalemaos/multitessiocr
Author: Johannes Fischer
Author-email: aulasparticularesdealemaosp@gmail.com
License: MIT
Keywords: tesseract,ocr,grouping
Classifier: Development Status :: 4 - Beta
Classifier: Programming Language :: Python :: 3 :: Only
Classifier: Programming Language :: Python :: 3.10
Classifier: Topic :: Software Development :: Libraries :: Python Modules
Classifier: Topic :: Utilities
License-File: LICENSE.rst
Requires-Dist: a-cv-imwrite-imread-plus
Requires-Dist: a-pandas-ex-apply-ignore-exceptions
Requires-Dist: lxml
Requires-Dist: multiprocca
Requires-Dist: numpy
Requires-Dist: opencv-python
Requires-Dist: pandas
Requires-Dist: touchtouch
